<annotation verified="yes">
	<folder>croppedImages</folder>
	<filename>reimage0197.png</filename>
	<path>/home/ethan/images/labled/croppedImages/reimage0197.png</path>
	<source>
		<database>Unknown</database>
	</source>
	<size>
		<width>256</width>
		<height>256</height>
		<depth>3</depth>
	</size>
	<segmented>0</segmented>
	<object>
		<name>Blue</name>
		<pose>Unspecified</pose>
		<truncated>0</truncated>
		<difficult>0</difficult>
		<bndbox>
			<xmin>45</xmin>
			<ymin>179</ymin>
			<xmax>70</xmax>
			<ymax>196</ymax>
		</bndbox>
	</object>
	<object>
		<name>Blue</name>
		<pose>Unspecified</pose>
		<truncated>0</truncated>
		<difficult>0</difficult>
		<bndbox>
			<xmin>108</xmin>
			<ymin>179</ymin>
			<xmax>126</xmax>
			<ymax>194</ymax>
		</bndbox>
	</object>
	<object>
		<name>Dead</name>
		<pose>Unspecified</pose>
		<truncated>0</truncated>
		<difficult>0</difficult>
		<bndbox>
			<xmin>151</xmin>
			<ymin>195</ymin>
			<xmax>189</xmax>
			<ymax>218</ymax>
		</bndbox>
	</object>
	<object>
		<name>Dead</name>
		<pose>Unspecified</pose>
		<truncated>0</truncated>
		<difficult>0</difficult>
		<bndbox>
			<xmin>156</xmin>
			<ymin>179</ymin>
			<xmax>194</xmax>
			<ymax>194</ymax>
		</bndbox>
	</object>
	<object>
		<name>Robot</name>
		<pose>Unspecified</pose>
		<truncated>0</truncated>
		<difficult>0</difficult>
		<bndbox>
			<xmin>137</xmin>
			<ymin>78</ymin>
			<xmax>237</xmax>
			<ymax>225</ymax>
		</bndbox>
	</object>
	<object>
		<name>Robot</name>
		<pose>Unspecified</pose>
		<truncated>0</truncated>
		<difficult>0</difficult>
		<bndbox>
			<xmin>20</xmin>
			<ymin>88</ymin>
			<xmax>142</xmax>
			<ymax>225</ymax>
		</bndbox>
	</object>
</annotation>
