<annotation verified="yes">
	<folder>croppedImages</folder>
	<filename>reimage0141.png</filename>
	<path>/home/ethan/images/labled/croppedImages/reimage0141.png</path>
	<source>
		<database>Unknown</database>
	</source>
	<size>
		<width>256</width>
		<height>256</height>
		<depth>3</depth>
	</size>
	<segmented>0</segmented>
	<object>
		<name>Blue</name>
		<pose>Unspecified</pose>
		<truncated>0</truncated>
		<difficult>0</difficult>
		<bndbox>
			<xmin>71</xmin>
			<ymin>130</ymin>
			<xmax>94</xmax>
			<ymax>145</ymax>
		</bndbox>
	</object>
	<object>
		<name>Blue</name>
		<pose>Unspecified</pose>
		<truncated>0</truncated>
		<difficult>0</difficult>
		<bndbox>
			<xmin>27</xmin>
			<ymin>129</ymin>
			<xmax>49</xmax>
			<ymax>147</ymax>
		</bndbox>
	</object>
	<object>
		<name>Blue</name>
		<pose>Unspecified</pose>
		<truncated>0</truncated>
		<difficult>0</difficult>
		<bndbox>
			<xmin>16</xmin>
			<ymin>44</ymin>
			<xmax>35</xmax>
			<ymax>59</ymax>
		</bndbox>
	</object>
	<object>
		<name>Dead</name>
		<pose>Unspecified</pose>
		<truncated>0</truncated>
		<difficult>0</difficult>
		<bndbox>
			<xmin>72</xmin>
			<ymin>81</ymin>
			<xmax>106</xmax>
			<ymax>106</ymax>
		</bndbox>
	</object>
	<object>
		<name>Dead</name>
		<pose>Unspecified</pose>
		<truncated>0</truncated>
		<difficult>0</difficult>
		<bndbox>
			<xmin>134</xmin>
			<ymin>94</ymin>
			<xmax>160</xmax>
			<ymax>115</ymax>
		</bndbox>
	</object>
	<object>
		<name>Robot</name>
		<pose>Unspecified</pose>
		<truncated>1</truncated>
		<difficult>0</difficult>
		<bndbox>
			<xmin>46</xmin>
			<ymin>1</ymin>
			<xmax>171</xmax>
			<ymax>125</ymax>
		</bndbox>
	</object>
	<object>
		<name>Robot</name>
		<pose>Unspecified</pose>
		<truncated>1</truncated>
		<difficult>0</difficult>
		<bndbox>
			<xmin>1</xmin>
			<ymin>1</ymin>
			<xmax>59</xmax>
			<ymax>84</ymax>
		</bndbox>
	</object>
	<object>
		<name>Robot</name>
		<pose>Unspecified</pose>
		<truncated>0</truncated>
		<difficult>0</difficult>
		<bndbox>
			<xmin>2</xmin>
			<ymin>90</ymin>
			<xmax>112</xmax>
			<ymax>167</ymax>
		</bndbox>
	</object>
</annotation>
